{
  "get": "players/squads",
  "parameters": {
    "team": "2082"
  },
  "errors": [],
  "results": 1,
  "paging": {
    "current": 1,
    "total": 1
  },
  "response": [
    {
      "team": {
        "id": 2082,
        "name": "Gnistan",
        "logo": "https://media.api-sports.io/football/teams/2082.png"
      },
      "players": [
        {
          "id": 558979,
          "name": "A. Craninx",
          "age": 29,
          "number": 1,
          "position": "Goalkeeper",
          "photo": "https://media.api-sports.io/football/players/558979.png"
        },
        {
          "id": 639620,
          "name": "S. Huttunen",
          "age": 17,
          "number": 13,
          "position": "Goalkeeper",
          "photo": "https://media.api-sports.io/football/players/639620.png"
        },
        {
          "id": 173931,
          "name": "O. Lyberopoulos",
          "age": 23,
          "number": 13,
          "position": "Goalkeeper",
          "photo": "https://media.api-sports.io/football/players/173931.png"
        },
        {
          "id": 546426,
          "name": "Ramilson",
          "age": 26,
          "number": 32,
          "position": "Goalkeeper",
          "photo": "https://media.api-sports.io/football/players/546426.png"
        },
        {
          "id": 319214,
          "name": "M. Bjurstr\u00f8m",
          "age": 19,
          "number": 25,
          "position": "Defender",
          "photo": "https://media.api-sports.io/football/players/319214.png"
        },
        {
          "id": 635067,
          "name": "Y. Boughalmi",
          "age": 15,
          "number": 34,
          "position": "Defender",
          "photo": "https://media.api-sports.io/football/players/635067.png"
        },
        {
          "id": 313306,
          "name": "B. Dahlstr\u00f6m",
          "age": 22,
          "number": 2,
          "position": "Defender",
          "photo": "https://media.api-sports.io/football/players/313306.png"
        },
        {
          "id": 546330,
          "name": "R. Gnanou",
          "age": 20,
          "number": 24,
          "position": "Defender",
          "photo": "https://media.api-sports.io/football/players/546330.png"
        },
        {
          "id": 584585,
          "name": "S. Heikari",
          "age": 16,
          "number": 22,
          "position": "Defender",
          "photo": "https://media.api-sports.io/football/players/584585.png"
        },
        {
          "id": 635066,
          "name": "Marcelo Costa",
          "age": 24,
          "number": 4,
          "position": "Defender",
          "photo": "https://media.api-sports.io/football/players/635066.png"
        },
        {
          "id": 635068,
          "name": "T. Minchev",
          "age": 19,
          "number": 17,
          "position": "Defender",
          "photo": "https://media.api-sports.io/football/players/635068.png"
        },
        {
          "id": 544713,
          "name": "A. Obileye",
          "age": 31,
          "number": 67,
          "position": "Defender",
          "photo": "https://media.api-sports.io/football/players/544713.png"
        },
        {
          "id": 48013,
          "name": "J. Ojala",
          "age": 36,
          "number": 40,
          "position": "Defender",
          "photo": "https://media.api-sports.io/football/players/48013.png"
        },
        {
          "id": 573838,
          "name": "M. Yinkfu Chuye",
          "age": 15,
          "number": 34,
          "position": "Defender",
          "photo": "https://media.api-sports.io/football/players/573838.png"
        },
        {
          "id": 340222,
          "name": "L. von Hellens",
          "age": 20,
          "number": 5,
          "position": "Defender",
          "photo": "https://media.api-sports.io/football/players/340222.png"
        },
        {
          "id": 53603,
          "name": "E. Bashkirov",
          "age": 34,
          "number": 44,
          "position": "Midfielder",
          "photo": "https://media.api-sports.io/football/players/53603.png"
        },
        {
          "id": 53526,
          "name": "R. Eremenko",
          "age": 38,
          "number": 26,
          "position": "Midfielder",
          "photo": "https://media.api-sports.io/football/players/53526.png"
        },
        {
          "id": 558968,
          "name": "S. Eremenko",
          "age": 26,
          "number": 14,
          "position": "Midfielder",
          "photo": "https://media.api-sports.io/football/players/558968.png"
        },
        {
          "id": 410218,
          "name": "G. Europaeus",
          "age": 20,
          "number": 15,
          "position": "Midfielder",
          "photo": "https://media.api-sports.io/football/players/410218.png"
        },
        {
          "id": 634745,
          "name": "Z. Fraser Grante",
          "age": 20,
          "number": 27,
          "position": "Midfielder",
          "photo": "https://media.api-sports.io/football/players/634745.png"
        },
        {
          "id": 263957,
          "name": "O. G\u00fcnes",
          "age": 23,
          "number": 25,
          "position": "Midfielder",
          "photo": "https://media.api-sports.io/football/players/263957.png"
        },
        {
          "id": 641201,
          "name": "J. Hakala",
          "age": null,
          "number": 18,
          "position": "Midfielder",
          "photo": "https://media.api-sports.io/football/players/641201.png"
        },
        {
          "id": 635069,
          "name": "T. Hamalainen",
          "age": null,
          "number": 2,
          "position": "Midfielder",
          "photo": "https://media.api-sports.io/football/players/635069.png"
        },
        {
          "id": 263880,
          "name": "V. H\u00e4nninen",
          "age": 23,
          "number": 19,
          "position": "Midfielder",
          "photo": "https://media.api-sports.io/football/players/263880.png"
        },
        {
          "id": 340121,
          "name": "O. Hannula",
          "age": 20,
          "number": 27,
          "position": "Midfielder",
          "photo": "https://media.api-sports.io/football/players/340121.png"
        },
        {
          "id": 560607,
          "name": "A. Jouhi",
          "age": 19,
          "number": 31,
          "position": "Midfielder",
          "photo": "https://media.api-sports.io/football/players/560607.png"
        },
        {
          "id": 55733,
          "name": "J. Latonen",
          "age": 27,
          "number": 10,
          "position": "Midfielder",
          "photo": "https://media.api-sports.io/football/players/55733.png"
        },
        {
          "id": 17733,
          "name": "K. Woolery",
          "age": 30,
          "number": 18,
          "position": "Midfielder",
          "photo": "https://media.api-sports.io/football/players/17733.png"
        },
        {
          "id": 57260,
          "name": "A. Akinyemi",
          "age": 27,
          "number": 17,
          "position": "Attacker",
          "photo": "https://media.api-sports.io/football/players/57260.png"
        },
        {
          "id": 196373,
          "name": "E. Arko-Mensah",
          "age": 24,
          "number": 12,
          "position": "Attacker",
          "photo": "https://media.api-sports.io/football/players/196373.png"
        },
        {
          "id": 410178,
          "name": "A. Atarah",
          "age": 20,
          "number": 20,
          "position": "Attacker",
          "photo": "https://media.api-sports.io/football/players/410178.png"
        },
        {
          "id": 470341,
          "name": "E. Lappalainen",
          "age": 18,
          "number": 21,
          "position": "Attacker",
          "photo": "https://media.api-sports.io/football/players/470341.png"
        },
        {
          "id": 584586,
          "name": "K. Launiala",
          "age": 15,
          "number": 28,
          "position": "Attacker",
          "photo": "https://media.api-sports.io/football/players/584586.png"
        },
        {
          "id": 589503,
          "name": "Jeff Selenge",
          "age": 15,
          "number": 6,
          "position": "Attacker",
          "photo": "https://media.api-sports.io/football/players/589503.png"
        }
      ]
    }
  ]
}